shellcheck_gha/__init__.py
shellcheck_gha/console/__init__.py
shellcheck_gha/console/app.py
shellcheck_gha/console/colors.py
shellcheck_gha/console/result_renderer.py
shellcheck_gha/extractor.py
shellcheck_gha/models/__init__.py
shellcheck_gha/models/github_action.py
shellcheck_gha/models/shell_check_json1.py
shellcheck_gha-0.1.2.dist-info/LICENSE
shellcheck_gha-0.1.2.dist-info/METADATA
shellcheck_gha-0.1.2.dist-info/WHEEL
shellcheck_gha-0.1.2.dist-info/entry_points.txt
shellcheck_gha-0.1.2.dist-info/RECORD
