Metadata-Version: 2.1
Name: shellcheck-gha
Version: 0.1.2
Summary: Extracts and checks shell scripts in Github Workflows for potential issues using shellcheck (https://github.com/koalaman/shellcheck).
Home-page: https://github.com/saleor/shellcheck-gha
License: BSD-3-Clause
Keywords: linter,static-analysis,shell,bash,dash,github,workflows,shellcheck
Author: Saleor Commerce
Author-email: hello@saleor.io
Requires-Python: >=3.11
Classifier: Development Status :: 1 - Planning
Classifier: Environment :: Console
Classifier: License :: OSI Approved :: BSD License
Classifier: Programming Language :: Python :: 3
Classifier: Programming Language :: Python :: 3.11
Classifier: Programming Language :: Python :: 3.12
Classifier: Programming Language :: Python :: 3 :: Only
Classifier: Programming Language :: Python :: 3.13
Classifier: Topic :: Security
Classifier: Topic :: Software Development :: Quality Assurance
Requires-Dist: jinja2 (>=3.1.3,<4.0.0)
Requires-Dist: pydantic (>=2.6.0,<3.0.0)
Requires-Dist: pyyaml (>=6.0.1,<7.0.0)
Project-URL: Repository, https://github.com/saleor/shellcheck-gha
